LICENSE
README.md
setup.py
ez_elb/EzElb.py
ez_elb/EzElb_0_3.py
ez_elb/EzElb_0_4.py
ez_elb/EzElb_0_5.py
ez_elb/__init__.py
ez_elb.egg-info/PKG-INFO
ez_elb.egg-info/SOURCES.txt
ez_elb.egg-info/dependency_links.txt
ez_elb.egg-info/requires.txt
ez_elb.egg-info/top_level.txt