Metadata-Version: 2.1
Name: ez-elb
Version: 0.7.0
Summary: Easily define complex ELB CloudFormation templates
Home-page: https://github.com/dboitnot/ez_elb
Author: Dan Boitnott
Author-email: boitnott@sigcorp.com
License: UNKNOWN
Platform: UNKNOWN
Classifier: Programming Language :: Python :: 2
Classifier: License :: OSI Approved :: MIT License
Classifier: Operating System :: OS Independent
License-File: LICENSE
